{
  "title": "Advanced Settings",
  "elements": [
    {"type": "checkbox", "label": "Show advanced options", "default": false},
    {
      "type": "conditional",
      "condition": "Show advanced options",
      "elements": [
        {"type": "checkbox", "label": "Debug mode", "default": false},
        {"type": "slider", "label": "Log level", "min": 0, "max": 10, "default": 3},
        {"type": "multiselect", "label": "Output", "options": ["Console", "File", "Both"]},
        {"type": "slider", "label": "Max threads", "min": 1, "max": 16, "default": 4}
      ]
    },
    {"type": "checkbox", "label": "Performance mode", "default": true},
    {
      "type": "conditional",
      "condition": "Performance mode",
      "elements": [
        {"type": "checkbox", "label": "GPU acceleration", "default": true},
        {"type": "slider", "label": "Cache size", "min": 0, "max": 1000, "default": 256}
      ]
    }
  ]
}